netbox_cybex/__init__.py
netbox_cybex/filtersets.py
netbox_cybex/forms.py
netbox_cybex/graphql.py
netbox_cybex/models.py
netbox_cybex/navigation.py
netbox_cybex/search.py
netbox_cybex/tables.py
netbox_cybex/urls.py
netbox_cybex/views.py
netbox_cybex/api/__init__.py
netbox_cybex/api/serializers.py
netbox_cybex/api/urls.py
netbox_cybex/api/views.py
netbox_cybex/migrations/0001_initial.py
netbox_cybex/migrations/__init__.py
netbox_cybex-0.1.dist-info/METADATA
netbox_cybex-0.1.dist-info/WHEEL
netbox_cybex-0.1.dist-info/top_level.txt
netbox_cybex-0.1.dist-info/RECORD
