Metadata-Version: 2.1
Name: netbox_cybex
Version: 0.1
Summary: Features for cyber exercises in NetBox
